{
  "scan_date": "2026-06-20T11:00:04",
  "etf_signals": [
    {
      "ticker": "SOXX",
      "current_rv": 97.2,
      "baseline_rv": 34.7,
      "z_score": 5.38,
      "vrp": -0.299,
      "beta_30d": 3.562,
      "consec_vol": 5,
      "excess_10d": 8.72,
      "level": 3,
      "label": "HIGH",
      "reason": "vol z=5.4, VRP=-0.299, beta=3.56, 5d consec vol",
      "sector": "Semiconductors"
    },
    {
      "ticker": "XLK",
      "current_rv": 53.9,
      "baseline_rv": 21.1,
      "z_score": 4.94,
      "vrp": -0.1605,
      "beta_30d": 2.184,
      "consec_vol": 5,
      "excess_10d": 0.65,
      "level": 3,
      "label": "HIGH",
      "reason": "vol z=4.9, VRP=-0.160, beta=2.18, 5d consec vol",
      "sector": "Technology"
    },
    {
      "ticker": "EWY",
      "current_rv": 115.0,
      "baseline_rv": 41.4,
      "z_score": 3.64,
      "vrp": -0.3036,
      "beta_30d": 4.639,
      "consec_vol": 5,
      "excess_10d": 10.67,
      "level": 3,
      "label": "HIGH",
      "reason": "vol z=3.6, VRP=-0.304, beta=4.64, 5d consec vol",
      "sector": "Korea (MSCI)"
    },
    {
      "ticker": "EEM",
      "current_rv": 50.6,
      "baseline_rv": 19.8,
      "z_score": 3.33,
      "vrp": -0.1179,
      "beta_30d": 2.1,
      "consec_vol": 5,
      "excess_10d": 4.43,
      "level": 3,
      "label": "HIGH",
      "reason": "vol z=3.3, VRP=-0.118, beta=2.10, 5d consec vol",
      "sector": "Emerging Markets"
    },
    {
      "ticker": "XLB",
      "current_rv": 29.0,
      "baseline_rv": 16.6,
      "z_score": 2.87,
      "vrp": -0.0653,
      "beta_30d": 0.983,
      "consec_vol": 5,
      "excess_10d": 1.54,
      "level": 3,
      "label": "HIGH",
      "reason": "vol z=2.9, VRP=-0.065, 5d consec vol",
      "sector": "Materials"
    },
    {
      "ticker": "XLI",
      "current_rv": 27.6,
      "baseline_rv": 16.1,
      "z_score": 2.48,
      "vrp": -0.0314,
      "beta_30d": 0.916,
      "consec_vol": 5,
      "excess_10d": 3.83,
      "level": 1,
      "label": "WATCH",
      "reason": "vol z=2.5, 5d consec vol",
      "sector": "Industrials"
    },
    {
      "ticker": "^KS11",
      "current_rv": 82.6,
      "baseline_rv": 35.6,
      "z_score": 2.09,
      "vrp": -0.2027,
      "beta_30d": 1.871,
      "consec_vol": 5,
      "excess_10d": 3.63,
      "level": 2,
      "label": "ALERT",
      "reason": "vol z=2.1, VRP=-0.203, beta=1.87, 5d consec vol",
      "sector": "KOSPI"
    },
    {
      "ticker": "XAR",
      "current_rv": 42.3,
      "baseline_rv": 27.5,
      "z_score": 1.82,
      "vrp": 0.0062,
      "beta_30d": 1.483,
      "consec_vol": 5,
      "excess_10d": 2.71,
      "level": 1,
      "label": "WATCH",
      "reason": "vol z=1.8, beta=1.48, 5d consec vol",
      "sector": "Defense / Aerospace"
    },
    {
      "ticker": "EWJ",
      "current_rv": 32.3,
      "baseline_rv": 18.8,
      "z_score": 1.82,
      "vrp": -0.0469,
      "beta_30d": 1.148,
      "consec_vol": 5,
      "excess_10d": 4.0,
      "level": 1,
      "label": "WATCH",
      "reason": "vol z=1.8, 5d consec vol",
      "sector": "Japan (MSCI)"
    },
    {
      "ticker": "XLY",
      "current_rv": 26.1,
      "baseline_rv": 18.2,
      "z_score": 1.64,
      "vrp": -0.0068,
      "beta_30d": 1.074,
      "consec_vol": 5,
      "excess_10d": 0.74,
      "level": 1,
      "label": "WATCH",
      "reason": "5d consec vol",
      "sector": "Consumer Discretionary"
    },
    {
      "ticker": "ES=F",
      "current_rv": 17.9,
      "baseline_rv": 12.0,
      "z_score": 1.58,
      "vrp": -0.0501,
      "beta_30d": 0.992,
      "consec_vol": 5,
      "excess_10d": -0.11,
      "level": 1,
      "label": "WATCH",
      "reason": "VRP=-0.050, 5d consec vol",
      "sector": "S&P 500 Futures"
    },
    {
      "ticker": "^N225",
      "current_rv": 39.0,
      "baseline_rv": 25.6,
      "z_score": 1.53,
      "vrp": -0.0834,
      "beta_30d": 0.557,
      "consec_vol": 5,
      "excess_10d": 6.5,
      "level": 1,
      "label": "WATCH",
      "reason": "VRP=-0.083, beta=0.56, 5d consec vol",
      "sector": "Nikkei 225"
    },
    {
      "ticker": "XLC",
      "current_rv": 17.0,
      "baseline_rv": 12.6,
      "z_score": 1.24,
      "vrp": 0.0109,
      "beta_30d": 0.519,
      "consec_vol": 5,
      "excess_10d": -2.21,
      "level": 1,
      "label": "WATCH",
      "reason": "beta=0.52, 5d consec vol",
      "sector": "Communication"
    },
    {
      "ticker": "XTN",
      "current_rv": 34.8,
      "baseline_rv": 26.6,
      "z_score": 0.87,
      "vrp": -0.0094,
      "beta_30d": 1.189,
      "consec_vol": 5,
      "excess_10d": 2.56,
      "level": 1,
      "label": "WATCH",
      "reason": "5d consec vol",
      "sector": "Transportation / Shipping"
    },
    {
      "ticker": "XLE",
      "current_rv": 25.2,
      "baseline_rv": 20.6,
      "z_score": 0.86,
      "vrp": 0.0246,
      "beta_30d": -0.511,
      "consec_vol": 5,
      "excess_10d": -7.68,
      "level": 1,
      "label": "WATCH",
      "reason": "beta=-0.51, 5d consec vol",
      "sector": "Energy / Oil"
    },
    {
      "ticker": "GLD",
      "current_rv": 38.1,
      "baseline_rv": 25.4,
      "z_score": 0.84,
      "vrp": -0.1061,
      "beta_30d": 1.429,
      "consec_vol": 5,
      "excess_10d": -4.75,
      "level": 1,
      "label": "WATCH",
      "reason": "VRP=-0.106, beta=1.43, 5d consec vol",
      "sector": "Gold"
    },
    {
      "ticker": "000001.SS",
      "current_rv": 16.4,
      "baseline_rv": 13.0,
      "z_score": 0.76,
      "vrp": -0.0211,
      "beta_30d": 0.207,
      "consec_vol": 5,
      "excess_10d": 2.32,
      "level": 1,
      "label": "WATCH",
      "reason": "beta=0.21, 5d consec vol",
      "sector": "Shanghai Composite"
    },
    {
      "ticker": "^FTSE",
      "current_rv": 14.4,
      "baseline_rv": 10.9,
      "z_score": 0.75,
      "vrp": 0.0296,
      "beta_30d": 0.269,
      "consec_vol": 5,
      "excess_10d": 3.41,
      "level": 1,
      "label": "WATCH",
      "reason": "beta=0.27, 5d consec vol",
      "sector": "FTSE 100"
    },
    {
      "ticker": "ZN=F",
      "current_rv": 4.7,
      "baseline_rv": 3.9,
      "z_score": 0.74,
      "vrp": 0.0067,
      "beta_30d": 0.215,
      "consec_vol": 5,
      "excess_10d": 1.1,
      "level": 1,
      "label": "WATCH",
      "reason": "beta=0.21, 5d consec vol",
      "sector": "10Y Treasury Futures"
    },
    {
      "ticker": "EWU",
      "current_rv": 18.0,
      "baseline_rv": 14.7,
      "z_score": 0.61,
      "vrp": 0.045,
      "beta_30d": 0.747,
      "consec_vol": 5,
      "excess_10d": 2.08,
      "level": 1,
      "label": "WATCH",
      "reason": "5d consec vol",
      "sector": "UK (MSCI)"
    },
    {
      "ticker": "GC=F",
      "current_rv": 34.5,
      "baseline_rv": 25.7,
      "z_score": 0.6,
      "vrp": -0.0635,
      "beta_30d": 0.898,
      "consec_vol": 5,
      "excess_10d": -4.5,
      "level": 1,
      "label": "WATCH",
      "reason": "VRP=-0.064, 5d consec vol",
      "sector": "Gold Futures"
    },
    {
      "ticker": "TLT",
      "current_rv": 9.2,
      "baseline_rv": 9.2,
      "z_score": 0.04,
      "vrp": 0.0049,
      "beta_30d": 0.341,
      "consec_vol": 5,
      "excess_10d": 2.49,
      "level": 1,
      "label": "WATCH",
      "reason": "beta=0.34, 5d consec vol",
      "sector": "Long-term Treasury"
    },
    {
      "ticker": "^FTMC",
      "current_rv": 11.7,
      "baseline_rv": 12.1,
      "z_score": -0.08,
      "vrp": 0.0574,
      "beta_30d": 0.412,
      "consec_vol": 5,
      "excess_10d": 2.48,
      "level": 1,
      "label": "WATCH",
      "reason": "beta=0.41, 5d consec vol",
      "sector": "FTSE 250 (UK 내수)"
    },
    {
      "ticker": "XLV",
      "current_rv": 13.9,
      "baseline_rv": 14.2,
      "z_score": -0.09,
      "vrp": 0.0489,
      "beta_30d": 0.044,
      "consec_vol": 4,
      "excess_10d": -0.72,
      "level": 1,
      "label": "WATCH",
      "reason": "beta=0.04",
      "sector": "Healthcare"
    },
    {
      "ticker": "CL=F",
      "current_rv": 42.8,
      "baseline_rv": 46.4,
      "z_score": -0.12,
      "vrp": 0.3294,
      "beta_30d": -0.948,
      "consec_vol": 5,
      "excess_10d": -17.91,
      "level": 1,
      "label": "WATCH",
      "reason": "beta=-0.95, 5d consec vol",
      "sector": "WTI Crude Futures"
    },
    {
      "ticker": "FXI",
      "current_rv": 19.2,
      "baseline_rv": 19.9,
      "z_score": -0.13,
      "vrp": 0.0525,
      "beta_30d": 0.602,
      "consec_vol": 3,
      "excess_10d": -4.46,
      "level": 1,
      "label": "WATCH",
      "reason": "beta=0.60",
      "sector": "China Large-Cap"
    },
    {
      "ticker": "XLF",
      "current_rv": 13.7,
      "baseline_rv": 14.4,
      "z_score": -0.16,
      "vrp": 0.0383,
      "beta_30d": 0.183,
      "consec_vol": 4,
      "excess_10d": 3.67,
      "level": 1,
      "label": "WATCH",
      "reason": "beta=0.18",
      "sector": "Financials / Banking"
    },
    {
      "ticker": "MCHI",
      "current_rv": 19.1,
      "baseline_rv": 20.3,
      "z_score": -0.22,
      "vrp": 0.0547,
      "beta_30d": 0.675,
      "consec_vol": 2,
      "excess_10d": -3.69,
      "level": 1,
      "label": "WATCH",
      "reason": "beta=0.67",
      "sector": "China Broad (MSCI)"
    },
    {
      "ticker": "^STOXX50E",
      "current_rv": 12.7,
      "baseline_rv": 15.1,
      "z_score": -0.37,
      "vrp": 0.0689,
      "beta_30d": 0.516,
      "consec_vol": 3,
      "excess_10d": 4.6,
      "level": 1,
      "label": "WATCH",
      "reason": "beta=0.52",
      "sector": "Euro Stoxx 50"
    },
    {
      "ticker": "^HSI",
      "current_rv": 16.7,
      "baseline_rv": 19.1,
      "z_score": -0.54,
      "vrp": 0.0185,
      "beta_30d": 0.248,
      "consec_vol": 2,
      "excess_10d": -4.31,
      "level": 1,
      "label": "WATCH",
      "reason": "beta=0.25",
      "sector": "Hang Seng"
    }
  ],
  "oil": {
    "level": 0,
    "reasons": []
  },
  "fred": [],
  "china": [
    {
      "sym": "sh000300",
      "label": "CSI300",
      "desc": "CSI 300 (중국 대형주)",
      "etfs": [
        "FXI",
        "MCHI"
      ],
      "current": 4885.25,
      "baseline": 4635.54,
      "z_score": 1.6,
      "rv_20d": 19.76,
      "last_date": "2026-06-18"
    },
    {
      "sym": "sh000905",
      "label": "CSI500",
      "desc": "CSI 500 (중국 중형주)",
      "etfs": [
        "MCHI"
      ],
      "current": 8464.22,
      "baseline": 7703.04,
      "z_score": 1.21,
      "rv_20d": 27.28,
      "last_date": "2026-06-18"
    },
    {
      "sym": "sz399006",
      "label": "ChiNext",
      "desc": "ChiNext (중국 성장/기술)",
      "etfs": [
        "MCHI"
      ],
      "current": 4077.25,
      "baseline": 3284.88,
      "z_score": 2.29,
      "rv_20d": 39.22,
      "last_date": "2026-06-18"
    },
    {
      "sym": "sh000001",
      "label": "Shanghai",
      "desc": "Shanghai Composite",
      "etfs": [
        "FXI",
        "MCHI"
      ],
      "current": 4083.69,
      "baseline": 3984.25,
      "z_score": 0.79,
      "rv_20d": 13.63,
      "last_date": "2026-06-18"
    }
  ],
  "flagged_count": 30,
  "alert_count": 6,
  "high_count": 5
}